CODING-STYLE.md
CONTRIBUTING.md
LICENSE
MANIFEST.in
NOTICE
README
README.md
mockapi.conf
requirements-test.txt
requirements.txt
setup.cfg
setup.py
docs/options.md
docs/test.md
features/__init__.py
features/archive.feature
features/basic.feature
features/certificate.feature
features/environment.py
features/fetch.feature
features/listarchives.feature
features/listcapsules.feature
features/login.feature
features/restore.feature
features/status.feature
features/upload.feature
features/upload_resume.feature
features/ClientInterface/CLI.py
features/ClientInterface/__init__.py
features/ClientInterface/constants.py
features/ClientInterface/ttypes.py
features/steps/__init__.py
features/steps/archive.py
features/steps/basic.py
lacli/__init__.py
lacli/basecmd.py
lacli/cache.py
lacli/capsule.py
lacli/certinput.py
lacli/cmdutil.py
lacli/command.py
lacli/compose.py
lacli/control.py
lacli/exceptions.py
lacli/hash.py
lacli/log.py
lacli/login.py
lacli/loginutil.py
lacli/main.py
lacli/main.rst
lacli/nice.py
lacli/pool.py
lacli/progress.py
lacli/registry.py
lacli/richtext.py
lacli/upload.py
lacli/upload_simple.py
lacli/worker.py
lacli.egg-info/PKG-INFO
lacli.egg-info/SOURCES.txt
lacli.egg-info/dependency_links.txt
lacli.egg-info/entry_points.txt
lacli.egg-info/requires.txt
lacli.egg-info/top_level.txt
lacli/archive/__init__.py
lacli/data/certificate.html
lacli/server/ClientInterface.thrift
lacli/server/__init__.py
lacli/server/error.py
lacli/server/cli/__init__.py
lacli/server/cli/ClientInterface/CLI.py
lacli/server/cli/ClientInterface/__init__.py
lacli/server/cli/ClientInterface/constants.py
lacli/server/cli/ClientInterface/ttypes.py
lacli/server/interface/__init__.py
lacli/server/interface/ClientInterface/CLI.py
lacli/server/interface/ClientInterface/__init__.py
lacli/server/interface/ClientInterface/constants.py
lacli/server/interface/ClientInterface/ttypes.py
lacli/source/__init__.py
lacli/source/chunked.py
lacli/t/__init__.py
lacli/t/test_archive.py
lacli/t/test_archive_command.py
lacli/t/test_cache.py
lacli/t/test_capsule_command.py
lacli/t/test_capsule_util.py
lacli/t/test_command.py
lacli/t/test_exceptions.py
lacli/t/test_fetch_command.py
