Metadata-Version: 1.1
Name: lacli
Version: 0.2.6.1
Summary: The Long Access client
Home-page: http://github.com/longaccess/longaccess-client/
Author: Konstantinos Koukopoulos
Author-email: kk@longaccess.com
License: Apache
Platform: UNKNOWN
Classifier: Development Status :: 4 - Beta
Classifier: Intended Audience :: Developers
Classifier: Intended Audience :: System Administrators
Classifier: Intended Audience :: Information Technology
Classifier: Natural Language :: English
Classifier: License :: OSI Approved :: Apache Software License
Classifier: Operating System :: OS Independent
Classifier: Programming Language :: Python
Classifier: Programming Language :: Python :: 2
Classifier: Programming Language :: Python :: 2.6
Classifier: Programming Language :: Python :: 2.7
Classifier: Topic :: System :: Archiving
Classifier: Topic :: Utilities
